animepixels/__init__.py
animepixels/client.py
animepixels-2.0.1.dist-info/licenses/LICENSE
animepixels-2.0.1.dist-info/METADATA
animepixels-2.0.1.dist-info/WHEEL
animepixels-2.0.1.dist-info/top_level.txt
animepixels-2.0.1.dist-info/RECORD
